dtlpy/__init__.py
dtlpy/__version__.py
dtlpy/exceptions.py
dtlpy/new_instance.py
dtlpy/assets/__init__.py
dtlpy/assets/lock_open.png
dtlpy/assets/main.py
dtlpy/assets/main_partial.py
dtlpy/assets/mock.json
dtlpy/assets/model_adapter.py
dtlpy/assets/package.json
dtlpy/assets/package_catalog.json
dtlpy/assets/package_gitignore
dtlpy/assets/project_dataset_recipe_ontology.png
dtlpy/assets/voc_annotation_template.xml
dtlpy/assets/code_server/config.yaml
dtlpy/assets/code_server/installation.sh
dtlpy/assets/code_server/launch.json
dtlpy/assets/code_server/settings.json
dtlpy/assets/service_runners/__init__.py
dtlpy/assets/service_runners/converter.py
dtlpy/assets/service_runners/multi_method.py
dtlpy/assets/service_runners/multi_method_annotation.py
dtlpy/assets/service_runners/multi_method_dataset.py
dtlpy/assets/service_runners/multi_method_item.py
dtlpy/assets/service_runners/multi_method_json.py
dtlpy/assets/service_runners/single_method.py
dtlpy/assets/service_runners/single_method_annotation.py
dtlpy/assets/service_runners/single_method_dataset.py
dtlpy/assets/service_runners/single_method_item.py
dtlpy/assets/service_runners/single_method_json.py
dtlpy/assets/service_runners/single_method_multi_input.py
dtlpy/caches/__init__.py
dtlpy/caches/base_cache.py
dtlpy/caches/cache.py
dtlpy/caches/dl_cache.py
dtlpy/caches/filesystem_cache.py
dtlpy/caches/redis_cache.py
dtlpy/dlp/__init__.py
dtlpy/dlp/cli_utilities.py
dtlpy/dlp/command_executor.py
dtlpy/dlp/dlp
dtlpy/dlp/dlp.bat
dtlpy/dlp/dlp.py
dtlpy/dlp/parser.py
dtlpy/entities/__init__.py
dtlpy/entities/analytic.py
dtlpy/entities/annotation.py
dtlpy/entities/annotation_collection.py
dtlpy/entities/app.py
dtlpy/entities/app_module.py
dtlpy/entities/artifact.py
dtlpy/entities/assignment.py
dtlpy/entities/base_entity.py
dtlpy/entities/bot.py
dtlpy/entities/codebase.py
dtlpy/entities/collection.py
dtlpy/entities/command.py
dtlpy/entities/compute.py
dtlpy/entities/dataset.py
dtlpy/entities/directory_tree.py
dtlpy-1.118.15.dist-info/licenses/LICENSE
dtlpy-1.118.15.dist-info/METADATA
dtlpy-1.118.15.dist-info/WHEEL
dtlpy-1.118.15.dist-info/entry_points.txt
dtlpy-1.118.15.dist-info/top_level.txt
dtlpy-1.118.15.dist-info/RECORD
