Metadata-Version: 2.4
Name: dtlpy
Version: 1.118.15
Summary: SDK and CLI for Dataloop platform
Home-page: https://github.com/dataloop-ai/dtlpy
Author: Dataloop Team
Author-email: info@dataloop.ai
License: Apache License 2.0
Classifier: Programming Language :: Python
Classifier: Programming Language :: Python :: 3
Classifier: Programming Language :: Python :: 3 :: Only
Classifier: Programming Language :: Python :: 3.10
Classifier: Programming Language :: Python :: 3.11
Classifier: Programming Language :: Python :: 3.12
Classifier: Programming Language :: Python :: 3.13
Classifier: Programming Language :: Python :: 3.14
Requires-Python: >=3.8
License-File: LICENSE
Requires-Dist: urllib3>=1.26
Requires-Dist: tqdm>=4.63
Requires-Dist: certifi>=2020.12.5
Requires-Dist: webvtt-py==0.4.3
Requires-Dist: aiohttp>=3.8
Requires-Dist: requests-toolbelt>=1.0.0
Requires-Dist: requests>=2.25.0
Requires-Dist: numpy>=1.16.2
Requires-Dist: pandas>=0.24.2
Requires-Dist: tabulate>=0.8.9
Requires-Dist: Pillow>=7.2
Requires-Dist: PyJWT>=2.4
Requires-Dist: jinja2>=2.11.3
Requires-Dist: attrs<25.0,>=22.2.0
Requires-Dist: prompt_toolkit>=2.0.9
Requires-Dist: fuzzyfinder<=2.1.0
Requires-Dist: dictdiffer>=0.8.1
Requires-Dist: validators<=0.18.2
Requires-Dist: pathspec>=0.8.1
Requires-Dist: filelock>=3.0.12
Requires-Dist: diskcache>=5.4
Requires-Dist: redis>=3.5
Requires-Dist: inquirer
Requires-Dist: dtlpymetrics
Requires-Dist: pymongo<5.0,>=4.9
Dynamic: author
Dynamic: author-email
Dynamic: classifier
Dynamic: description
Dynamic: description-content-type
Dynamic: home-page
Dynamic: license
Dynamic: license-file
Dynamic: requires-dist
Dynamic: requires-python
Dynamic: summary
